TransformationQA_ZongqianLi/__init__.py
TransformationQA_ZongqianLi/transformationqa.py
TransformationQA_ZongqianLi-3.0.0.dist-info/LICENSE
TransformationQA_ZongqianLi-3.0.0.dist-info/METADATA
TransformationQA_ZongqianLi-3.0.0.dist-info/WHEEL
TransformationQA_ZongqianLi-3.0.0.dist-info/top_level.txt
TransformationQA_ZongqianLi-3.0.0.dist-info/RECORD
