Metadata-Version: 2.1
Name: TransformationQA_ZongqianLi
Version: 3.0.0
Summary: Transform ChemDataExtractor generated databases into QA datasets.
Author-email: Zongqian Li <zongqianli.work@outlook.com>
Project-URL: Homepage, https://github.com/ZongqianLi/SolarCellBERT/tree/main
Project-URL: Bug Tracker, https://github.com/ZongqianLi/SolarCellBERT/tree/main
Classifier: Programming Language :: Python :: 3
Classifier: License :: OSI Approved :: MIT License
Classifier: Operating System :: OS Independent
License-File: LICENSE
